remote_log/__init__.py
remote_log/__main__.py
remote_log/remote_log.py
remote_log/sysinfo.py
remote_log/tests.py
remote_log-1.0.11.dist-info/METADATA
remote_log-1.0.11.dist-info/WHEEL
remote_log-1.0.11.dist-info/top_level.txt
remote_log-1.0.11.dist-info/RECORD
