Metadata-Version: 2.1
Name: remote-log
Version: 1.0.11
Summary: A simple function to send logging data to a remote server.
Author: Shubham Gupta
Author-email: shubhastro2@gmail.com
Requires-Dist: psutil
Requires-Dist: py-cpuinfo
Requires-Dist: requests
